[
    {
        "CLIENTE_ID": "AQUAMUNDO",
        "RAZON_SOCIAL": "AQUAMUNDO",
        "DOCUMENTO_ID": 345111,
        "STATUS": "D30",
        "TIPO_CPTE": "DE - DEVOLUCIONES",
        "COMPROBANTE": null,
        "FECHA_CPTE": 45061,
        "CANT_AUX": 12.0,
        "QTY_TOTAL": 12.0,
        "QTY_PEND_UBICAR": 12.0,
        "QTY_UBICADA": 0.0,
        "QTY_EGRESADA": 0.0,
        "FECHA_ALTA_OC": null,
        "ORDEN_DE_COMPRA": null,
        "FECHA_ALTA_GTW": "2023-05-15 11:36:26.000",
        "NRO_REMITO": null,
        "NDI": "49-131527",
        "OBSERVACIONES": null,
        "VALIDA_QTY": "OK"
    },
    {
        "CLIENTE_ID": "STAIB",
        "RAZON_SOCIAL": "SCYSE GLOBAL CHILE LTDA",
        "DOCUMENTO_ID": 1941,
        "STATUS": "D35",
        "TIPO_CPTE": "DO - DO",
        "COMPROBANTE": null,
        "FECHA_CPTE": 41675,
        "CANT_AUX": 104.0,
        "QTY_TOTAL": 104.0,
        "QTY_PEND_UBICAR": 0.0,
        "QTY_UBICADA": 0.0,
        "QTY_EGRESADA": 104.0,
        "FECHA_ALTA_OC": null,
        "ORDEN_DE_COMPRA": null,
        "FECHA_ALTA_GTW": "2014-02-18 18:00:07.170",
        "NRO_REMITO": null,
        "NDI": null,
        "OBSERVACIONES": "LETS BONUS",
        "VALIDA_QTY": "OK"
    },
    {
        "CLIENTE_ID": "AQUAMUNDO",
        "RAZON_SOCIAL": "AQUAMUNDO",
        "DOCUMENTO_ID": 338998,
        "STATUS": "D30",
        "TIPO_CPTE": "I01 - RECEPCION DE OC",
        "COMPROBANTE": null,
        "FECHA_CPTE": 44988,
        "CANT_AUX": 240.0,
        "QTY_TOTAL": 240.0,
        "QTY_PEND_UBICAR": 240.0,
        "QTY_UBICADA": 0.0,
        "QTY_EGRESADA": 0.0,
        "FECHA_ALTA_OC": "2023-02-27 16<a:13:1057517249809891348>58.280",
        "ORDEN_DE_COMPRA": "49-3439-1",
        "FECHA_ALTA_GTW": "2023-03-03 07:39:00.417",
        "NRO_REMITO": ".",
        "NDI": "2023022738717",
        "OBSERVACIONES": null,
        "VALIDA_QTY": "OK"
    },
    {
        "CLIENTE_ID": "ZTE CL003",
        "RAZON_SOCIAL": "ZTE CL003",
        "DOCUMENTO_ID": "344695",
        "STATUS": "D30",
        "TIPO_CPTE": "I01 - RECEPCION DE OC",
        "COMPROBANTE": null,
        "FECHA_CPTE": "45037",
        "CANT_AUX": "18.00000",
        "QTY_TOTAL": "18.00000",
        "QTY_PEND_UBICAR": "4.00000",
        "QTY_UBICADA": "14.00000",
        "QTY_EGRESADA": "0.00000",
        "FECHA_ALTA_OC": null,
        "ORDEN_DE_COMPRA": "DR2023041858345",
        "FECHA_ALTA_GTW": "2023-05-04 13:56:13.303",
        "NRO_REMITO": null,
        "NDI": "6 PALLETS",
        "OBSERVACIONES": null,
        "VALIDA_QTY": "OK"
    },
    {
        "CLIENTE_ID": "AQUAMUNDO",
        "RAZON_SOCIAL": "AQUAMUNDO",
        "DOCUMENTO_ID": "345116",
        "STATUS": "D30",
        "TIPO_CPTE": "DE - DEVOLUCIONES",
        "COMPROBANTE": null,
        "FECHA_CPTE": "45061",
        "CANT_AUX": "162.00000",
        "QTY_TOTAL": "162.00000",
        "QTY_PEND_UBICAR": "162.00000",
        "QTY_UBICADA": "0.00000",
        "QTY_EGRESADA": "0.00000",
        "FECHA_ALTA_OC": null,
        "ORDEN_DE_COMPRA": "49-130876",
        "FECHA_ALTA_GTW": null,
        "NRO_REMITO": null,
        "NDI": "OK",
        "OBSERVACIONES": null,
        "VALIDA_QTY": "OK"
    }
]